openpyxl_table_formatter/__init__.py
openpyxl_table_formatter-0.1.2.dist-info/WHEEL
openpyxl_table_formatter-0.1.2.dist-info/entry_points.txt
openpyxl_table_formatter-0.1.2.dist-info/METADATA
openpyxl_table_formatter-0.1.2.dist-info/RECORD
